ml_data_api/__init__.py
ml_data_api/data_api.py
ml_data_api-0.0.2.dist-info/METADATA
ml_data_api-0.0.2.dist-info/WHEEL
ml_data_api-0.0.2.dist-info/top_level.txt
ml_data_api-0.0.2.dist-info/RECORD
