Metadata-Version: 2.1
Name: ml-data-api
Version: 0.0.2
Summary: susallwave data api python sdk
Home-page: https://www.susallwave.com/
License: UNKNOWN
Platform: UNKNOWN
